[
  {
    "id": 1,
    "name":"Anu",
    "rollNo": "23CS001",
    "department": "Computer Science",
    "email": "anu@ksrce.ac.in",
    "phone": "+91 9876543210",
    "address": "Namakkal, Tamil Nadu",
    "dob": "20-04-2007",
    "year": "3rd Year",
    "semester": "6",
    "cgpa": 9.12,
    "attendance": 95,
    "credits": 126,
    "projects": 6,
    "achievements": "Best Student Award",
    "status": "Active",
    "image": "https://randomuser.me/api/portraits/women/65.jpg",
    "skills": ["React", "Java", "Python",
    "Java",
    "Node.js",
    "SQL",
    "UI Design"]
  },
  {
    "id": 2,
    "name": "Sharu",
    "rollNo": "23CS002",
    "department": "Computer Science",
    "email": "sharu@ksrce.ac.in",
    "phone": "+91 9876543211",
    "address": "Erode",
    "dob": "15-03-2007",
    "year": "3rd Year",
    "semester": "6",
    "cgpa": 8.91,
    "attendance": 92,
    "credits": 124,
    "projects": 5,
    "achievements": "Hackathon Winner",
    "status": "Active",
    "image": "https://randomuser.me/api/portraits/women/45.jpg",
    "skills": ["HTML", "CSS", "React"]
  },
  {
    "id": 3,
    "name": "Arun",
    "rollNo": "23CS003",
    "department": "Computer Science",
    "email": "arun@ksrce.ac.in",
    "phone": "+91 9876543212",
    "address": "Salem",
    "dob": "11-06-2006",
    "year": "3rd Year",
    "semester": "6",
    "cgpa": 8.45,
    "attendance": 88,
    "credits": 122,
    "projects": 4,
    "achievements": "Coding Contest Winner",
    "status": "Active",
    "image": "https://randomuser.me/api/portraits/men/20.jpg",
    "skills": ["Python", "SQL", "NodeJS"]
  },
  {
    "id": 4,
    "name": "Divya",
    "rollNo": "23CS004",
    "department": "Computer Science",
    "email": "divya@ksrce.ac.in",
    "phone": "+91 9876543213",
    "address": "Karur",
    "dob": "18-05-2007",
    "year": "3rd Year",
    "semester": "6",
    "cgpa": 9.02,
    "attendance": 91,
    "credits": 125,
    "projects": 5,
    "achievements": "Project Excellence Award",
    "status": "Active",
    "image": "https://randomuser.me/api/portraits/women/22.jpg",
    "skills": ["Java", "React", "MongoDB"]
  },
  {
    "id": 5,
    "name": "Kavin",
    "rollNo": "23CS005",
    "department": "Computer Science",
    "email": "kavin@ksrce.ac.in",
    "phone": "+91 9876543214",
    "address": "Trichy",
    "dob": "12-09-2006",
    "year": "3rd Year",
    "semester": "6",
    "cgpa": 8.78,
    "attendance": 85,
    "credits": 120,
    "projects": 5,
    "achievements": "Flutter Developer",
    "status": "On Leave",
    "image": "https://randomuser.me/api/portraits/men/34.jpg",
    "skills": ["Flutter", "Firebase", "Java"]
  },
  {
    "id": 6,
    "name": "Keerthana",
    "rollNo": "23CS006",
    "department": "Computer Science",
    "email": "keerthana@ksrce.ac.in",
    "phone": "+91 9876543215",
    "address": "Coimbatore",
    "dob": "09-02-2007",
    "year": "3rd Year",
    "semester": "6",
    "cgpa": 9.30,
    "attendance": 96,
    "credits": 128,
    "projects": 7,
    "achievements": "UI Design Champion",
    "status": "Active",
    "image": "https://randomuser.me/api/portraits/women/51.jpg",
    "skills": ["React", "Tailwind", "Node"]
  },
  {
    "id": 7,
    "name": "Praveen",
    "rollNo": "23CS007",
    "department": "Computer Science",
    "email": "praveen@ksrce.ac.in",
    "phone": "+91 9876543216",
    "address": "Madurai",
    "dob": "28-01-2007",
    "year": "3rd Year",
    "semester": "6",
    "cgpa": 8.75,
    "attendance": 90,
    "credits": 123,
    "projects": 5,
    "achievements": "AI Mini Project Winner",
    "status": "Active",
    "image": "https://randomuser.me/api/portraits/men/50.jpg",
    "skills": ["Python", "AI", "ML"]
  },
  {
    "id": 8,
    "name": "Sneha",
    "rollNo": "23CS008",
    "department": "Computer Science",
    "email": "sneha@ksrce.ac.in",
    "phone": "+91 9876543217",
    "address": "Chennai",
    "dob": "04-10-2007",
    "year": "3rd Year",
    "semester": "6",
    "cgpa": 9.41,
    "attendance": 97,
    "credits": 130,
    "projects": 7,
    "achievements": "Top Rank Holder",
    "status": "Active",
    "image": "https://randomuser.me/api/portraits/women/12.jpg",
    "skills": ["React", "Express", "MongoDB"]
  },
  {
    "id": 9,
    "name": "Vignesh",
    "rollNo": "23CS009",
    "department": "Computer Science",
    "email": "vignesh@ksrce.ac.in",
    "phone": "+91 9876543218",
    "address": "Namakkal",
    "dob": "17-12-2006",
    "year": "3rd Year",
    "semester": "6",
    "cgpa": 8.50,
    "attendance": 86,
    "credits": 121,
    "projects": 4,
    "achievements": "Spring Boot Developer",
    "status": "Graduated",
    "image": "https://randomuser.me/api/portraits/men/67.jpg",
    "skills": ["Java", "Spring", "SQL"]
  },
  {
    "id": 10,
    "name": "Priya",
    "rollNo": "23CS010",
    "department": "Computer Science",
    "email": "priya@ksrce.ac.in",
    "phone": "+91 9876543219",
    "address": "Erode",
    "dob": "02-11-2007",
    "year": "3rd Year",
    "semester": "6",
    "cgpa": 9.21,
    "attendance": 94,
    "credits": 127,
    "projects": 6,
    "achievements": "UI/UX Designer",
    "status": "Active",
    "image": "https://randomuser.me/api/portraits/women/66.jpg",
    "skills": ["React", "UI Design", "CSS"]
  },
  {
    "id": 11,
    "name": "Hari",
    "rollNo": "23CS011",
    "department": "Computer Science",
    "email": "hari@ksrce.ac.in",
    "phone": "+91 9876543220",
    "address": "Salem",
    "dob": "06-06-2007",
    "year": "3rd Year",
    "semester": "6",
    "cgpa": 8.61,
    "attendance": 89,
    "credits": 122,
    "projects": 4,
    "achievements": "Linux Administrator",
    "status": "Active",
    "image": "https://randomuser.me/api/portraits/men/74.jpg",
    "skills": ["Python", "C", "Linux"]
  },
  {
    "id": 12,
    "name": "Anitha",
    "rollNo": "23CS012",
    "department": "Computer Science",
    "email": "anitha@ksrce.ac.in",
    "phone": "+91 9876543221",
    "address": "Karur",
    "dob": "30-01-2007",
    "year": "3rd Year",
    "semester": "6",
    "cgpa": 8.95,
    "attendance": 91,
    "credits": 124,
    "projects": 5,
    "achievements": "Bootstrap Expert",
    "status": "Active",
    "image": "https://randomuser.me/api/portraits/women/39.jpg",
    "skills": ["React", "Bootstrap", "Java"]
  },
  {
    "id": 13,
    "name": "Rahul",
    "rollNo": "23CS013",
    "department": "Computer Science",
    "email": "rahul@ksrce.ac.in",
    "phone": "+91 9876543222",
    "address": "Madurai",
    "dob": "07-07-2006",
    "year": "3rd Year",
    "semester": "6",
    "cgpa": 8.20,
    "attendance": 84,
    "credits": 118,
    "projects": 4,
    "achievements": "Backend Developer",
    "status": "Active",
    "image": "https://randomuser.me/api/portraits/men/77.jpg",
    "skills": ["NodeJS", "Express", "MongoDB"]
  },
  {
    "id": 14,
    "name": "Lavanya",
    "rollNo": "23CS014",
    "department": "Computer Science",
    "email": "lavanya@ksrce.ac.in",
    "phone": "+91 9876543223",
    "address": "Chennai",
    "dob": "01-01-2007",
    "year": "3rd Year",
    "semester": "6",
    "cgpa": 9.50,
    "attendance": 98,
    "credits": 132,
    "projects": 8,
    "achievements": "Gold Medalist",
    "status": "Active",
    "image": "https://randomuser.me/api/portraits/women/70.jpg",
    "skills": ["React", "Angular", "Node"]
  },
  {
    "id": 15,
    "name": "Ajay",
    "rollNo": "23CS015",
    "department": "Computer Science",
    "email": "ajay@ksrce.ac.in",
    "phone": "+91 9876543224",
    "address": "Coimbatore",
    "dob": "16-08-2007",
    "year": "3rd Year",
    "semester": "6",
    "cgpa": 8.74,
    "attendance": 90,
    "credits": 123,
    "projects": 5,
    "achievements": "React Developer",
    "status": "Active",
    "image": "https://randomuser.me/api/portraits/men/91.jpg",
    "skills": ["Java", "Python", "React"]
  }
]